README.md
setup.cfg
setup.py
virt-back
virtback.py
virt_back.egg-info/PKG-INFO
virt_back.egg-info/SOURCES.txt
virt_back.egg-info/dependency_links.txt
virt_back.egg-info/requires.txt
virt_back.egg-info/top_level.txt