Metadata-Version: 2.1
Name: virt-back
Version: 0.2.2
Summary: virt-back: A backup utility for QEMU, KVM, XEN, and Virtualbox guests
Home-page: https://git.unturf.com/python/virt-back
Author: Russell Ballestrini
Author-email: russell@ballestrini.net
License: Public Domain
Keywords: backup virtual hypervisor QEMU KVM XEN Virtualbox
Platform: All
